Metadata-Version: 1.1
Name: jixian
Version: 1.0
Summary: set your encoding and logger
Home-page: https://github.com/Moxin1044/jixian
Author: Moxin
Author-email: lqn@jixiannet.com
License: proprietary
Keywords: pytest,py.test,pytest_encode
Platform: UNKNOWN
Classifier: Framework :: Pytest
Classifier: Programming Language :: Python
Classifier: Topic :: Software Development :: Testing
Classifier: Programming Language :: Python :: 3.8
